src/alu.sv
module alu (
	input signed [31:0] a,
	input signed [31:0] b,
	input [2:0] op,
	output reg signed [31:0] out
);
	
	always @(a or b or op) begin
		out <= a;
		case (op)
			3'b000 : out <= a + b;
			3'b001 : out <= a - b;
			3'b010 : out <= a << b;
			3'b011 : out <= a >> b;
			3'b100 : out <= a & b;
			3'b101 : out <= a >>> b;
			3'b110 : out <= a | b;
			3'b111 : out <= a ^ b;
		endcase
	end

endmodule

trace.vcd
$version Generated by VerilatedVcd $end
$timescale 1s $end
 $scope module TOP $end
  $var wire 32 # a [31:0] $end
  $var wire 32 $ b [31:0] $end
  $var wire 3 % op [2:0] $end
  $var wire 32 & out [31:0] $end
  $scope module alu $end
   $var wire 32 # a [31:0] $end
   $var wire 32 $ b [31:0] $end
   $var wire 3 % op [2:0] $end
   $var wire 32 & out [31:0] $end
  $upscope $end
 $upscope $end
$enddefinitions $end


#8
b00000000000000000000000000000000 #
b00000000000000000000000000000000 $
b000 %
b00000000000000000000000000000000 &
#10
b01011011111111110011100111011010 #
b10000000111000010011110010011111 $
b11011100111000000111011001111001 &
#15
#18
#20
b00001000101100000000110001111101 #
b00000101010010000010000000111101 $
b00001101111110000010110010111010 &
#25
#28
#30
b00110011111011101110111010011110 #
b01011010000101010111011110100111 $
b10001110000001000110011001000101 &
#35
#38
#40
b01111111110100111100111011100100 #
b00100110100010110011000011010100 $
b10100110010111101111111110111000 &
#45
#48
#50
b01100100110000010110000011010000 #
b10010001110001110010110010110110 $
b11110110100010001000110110000110 &
#55
#58
#60
b01000111110111011000001000010110 #
b11011010011101100001100101111110 $
b00100010010100111001101110010100 &
#65
#68
#70
b00001101101101011000100100111111 #
b10000010000111001000011101100010 $
b10001111110100100001000010100001 &
#75
#78
#80
b11001100010010100011010110111000 #
b11101000010100010001111111100011 $
b10110100100110110101010110011011 &
#85
#88
#90
b00110100011101010111100011001101 #
b01101101111101001000101011101101 $
b10100010011010100000001110111010 &
#95
#98
#100
b10000101100011000101100100101110 #
b00011011010101000001001100111101 $
b10100000111000000110110001101011 &
#105
#108
#110
b11101101011110111010101100011001 #
b00101011011000101110110011100110 $
b00011000110111101001011111111111 &
#115
#118
#120
b00100111110011101110010001110101 #
b11000110101101110111111001010110 $
b11101110100001100110001011001011 &
#125
#128
#130
b01000010101010101011111101101101 #
b11100111111011111101110100110101 $
b00101010100110101001110010100010 &
#135
#138
#140
b01001001010110110101100011010000 #
b10101010101000011111100011100100 $
b11110011111111010101000110110100 &
#145
#148
#150
b00101111001111101110100010010000 #
b01111110101000110010000110100111 $
b10101101111000100000101000110111 &
#155
#158
#160
b10001110000011111010110011001010 #
b01101101011110010000111000111101 $
b11111011100010001011101100000111 &
#165
#168
#170
b00111110001011100111101110011110 #
b00111100001110000000000111110100 $
b01111010011001100111110110010010 &
#175
#178
#180
b00000111010010101100001010000100 #
b10010111000011001101011111000100 $
b10011110010101111001101001001000 &
#185
#188
#190
b00000001101100111000000001000110 #
b11001000000111001001101100000001 $
b11001001110100000001101101000111 &
#195
#198
#200
b10100010100111111001000111000100 #
b00010000001100101110000100111001 $
b10110010110100100111001011111101 &
#205
#208
#210
b10011001100001100010101101011110 #
b10000111111101111101101100110101 $
b00100001011111100000011010010011 &
#215
#218
#220
b01011100000101011000110100110100 #
b10000010110110111010110001000000 $
b11011110111100010011100101110100 &
#225
#228
#230
b00100111111110110010110100111000 #
b00111011101000100110100101000000 $
b01100011100111011001011001111000 &
#235
#238
#240
b10101100010000010011111101110010 #
b00001000011111100000100010000100 $
b10110100101111110100011111110110 &
#245
#248
#250
b00101101110010100101011111111101 #
b01101000001010110111101011111111 $
b10010101111101011101001011111100 &
#255
#258
#260
b00010110001100110100000010110110 #
b00010000100100001100111101110110 $
b00100110110001000001000000101100 &
#265
#268
#270
b00111010010111000111101100011111 #
b10000111011100011111001111111001 $
b11000001110011100110111100011000 &
#275
#278
#280
b10110000010011110101000001101010 #
b01110010010100001110010111110111 $
b00100010101000000011011001100001 &
#285
#288
#290
b00100110011110000010000100110111 #
b11000101011010011100011010010101 $
b11101011111000011110011111001100 &
#295
#298
#300
b10101101111101110100011111010001 #
b00100111100111010110110010010011 $
b11010101100101001011010001100100 &
#305
#308
#310
b01110110111011010110100001000000 #
b11010000000100000000110111110100 $
b01000110111111010111011000110100 &
#315
#318
#320
b00110001111001010010100000001010 #
b00001010000011001010000111110000 $
b00111011111100011100100111111010 &
#325
#328
#330
b10001111111110100001110011010111 #
b10110100010100101100000110100000 $
b01000100010011001101111001110111 &
#335
#338
#340
b11000111110100011100011101010110 #
b11101000010101011100100000001111 $
b10110000001001111000111101100101 &
#345
#348
#350
b11000101010110010000010111111100 #
b10101010001010111100111011001100 $
b01101111100001001101010011001000 &
#355
#358
#360
b00001100001110010111101001100101 #
b10001100010100001100011010001110 $
b10011000100010100100000011110011 &
#365
#368
#370
b11101111111001111111111101100111 #
b11001011000010111011010111110110 $
b10111010111100111011010101011101 &
#375
#378
#380
b10100100010101111111111101000010 #
b01011111000010000100111010110010 $
b00000011011000000100110111110100 &
#385
#388
#390
b01010100001011111010110010010110 #
b00100101010101110110110011001100 $
b01111001100001110001100101100010 &
#395
#398
#400
b01100001100011101011010100111000 #
b00010110101000101100111011110111 $
b01111000001100011000010000101111 &
#405
#408
#410
b01101010100010101010100011010001 #
b00000101100011101100001110100101 $
b01110000000110010110110001110110 &
#415
#418
#420
b00010100100110011100100111100010 #
b11011011110011011111110001100110 $
b11110000011001111100011001001000 &
#425
#428
#430
b01100111101100010100110101110101 #
b10010000111101001000010111110011 $
b11111000101001011101001101101000 &
#435
#438
#440
b10111010010100011110010111000000 #
b01110110010011010010001000010001 $
b00110000100111110000011111010001 &
#445
#448
#450
b11111001101011001010010010011101 #
b11010000011101001000001011101110 $
b11001010001000010010011110001011 &
#455
#458
#460
b10101110110111110001101101111011 #
b00001011111100001111010100001101 $
b10111010110100000001000010001000 &
#465
#468
#470
b10111110110100010011010001011111 #
b11000111101000100100110000010100 $
b10000110011100111000000001110011 &
#475
#478
#480
b11000111011001011100110011100001 #
b01000111110011010000110111100000 $
b00001111001100101101101011000001 &
#485
#488
#490
b01000101111111001111010010101110 #
b00010001010101011010001001010000 $
b01010111010100101001011011111110 &
#495
#498
#500
b11000110010101001100101100111101 #
b01110111100001010101011010111100 $
b00111101110110100010000111111001 &
#505
#508
#510
b01101110010110001110100010001110 #
b01000101110010100011101101001101 $
b10110100001000110010001111011011 &
#515
#518
#520
b11101111010001110001111101101110 #
b01001101111010100001010101101001 $
b00111101001100010011010011010111 &
#525
#528
#530
b01000101101100011111011010000011 #
b11110000101001100000101010010011 $
b00110110010110000000000100010110 &
#535
#538
#540
b00010100011000100000100100110100 #
b01111001110000110010101100001101 $
b10001110001001010011010001000001 &
#545
#548
#550
b01000011111101011001101010100110 #
b01000111011101011011000111110001 $
b10001011011010110100110010010111 &
#555
#558
#560
b01001101101111111000010011111100 #
b10100100100101000100101111101110 $
b11110010010100111101000011101010 &
#565
#568
#570
b01111110110010011001001000010001 #
b10101110100000011110111110001100 $
b00101101010010111000000110011101 &
#575
#578
#580
b11100011100001010000111000110011 #
b00110100110100000010101110000000 $
b00011000010101010011100110110011 &
#585
#588
#590
b11000001100111101011100011000001 #
b00110110101101100110110100110010 $
b11111000010101010010010111110011 &
#595
#598
#600
b01100111101110101011010001011001 #
b01110100011001101101111101100110 $
b11011100001000011001001110111111 &
#605
#608
#610
b11011011011011111011010100110010 #
b01001111000101110100100001101000 $
b00101010100001101111110110011010 &
#615
#618
#620
b00010111011111001100011100100111 #
b01100111111001010001001001001101 $
b01111111011000011101100101110100 &
#625
#628
#630
b11001110001000110000011011111100 #
b10001011010101010011011000000001 $
b01011001011110000011110011111101 &
#635
#638
#640
b00110100010000001011011001010010 #
b00100010000101110100101001011000 $
b01010110010110000000000010101010 &
#645
#648
#650
b00010101101100010011000111111110 #
b01000011100111100010010110011011 $
b01011001010011110101011110011001 &
#655
#658
#660
b10010110101111011100001001110011 #
b01010111100110110001011000111001 $
b11101110010110001101100010101100 &
#665
#668
#670
b00001010100001010011010111111100 #
b10010111000110101111000011111010 $
b10100001101000000010011011110110 &
#675
#678
#680
b11110110100011010001011010010110 #
b10111101111110101001111001010011 $
b10110100100001111011010011101001 &
#685
#688
#690
b01001111111110111111101100111000 #
b00000000111010011110110011011101 $
b01010000111001011110100000010101 &
#695
#698
#700
b11100110001011111011111100101010 #
b11011010101101100000101001100101 $
b11000000111001011100100110001111 &
#705
#708
#710
b11011101011110111101100111110110 #
b11001100111110001011011101100001 $
b10101010011101001001000101010111 &
#715
#718
#720
b01001000111011101101011110011111 #
b10100101001101010100011100011010 $
b11101110001001000001111010111001 &
#725
#728
#730
b10010101001011101100000001100011 #
b11011111100100101011001011000100 $
b01110100110000010111001100100111 &
#735
#738
#740
b00111100001010000000000111110000 #
b11110111100000110111100111101101 $
b00110011101010110111101111011101 &
#745
#748
#750
b11001000100000010111100100110011 #
b00101110011001110000010010101011 $
b11110110111010000111110111011110 &
#755
#758
#760
b00100011010101111101000000000000 #
b01101001010000100100101111000100 $
b10001100100110100001101111000100 &
#765
#768
#770
b01010101101010011100011110100100 #
b10001011111110111101000001110111 $
b11100001101001011001100000011011 &
#775
#778
#780
b11011110101111001101101011010111 #
b10011110110110100111000010101110 $
b01111101100101110100101110000101 &
#785
#788
#790
b10111111111101001101100101111011 #
b10011100111000011001011010011001 $
b01011100110101100111000000010100 &
#795
#798
#800
b11011001001100001010110000010001 #
b01110110001011001111101111111010 $
b01001111010111011010100000001011 &
#805
#808
#810
b01110000101100000100100100001110 #
b10000010101001000111000000001011 $
b11110011010101001011100100011001 &
#815
#818
#820
b10001100001011100110101101010110 #
b11000001000101110100100111011101 $
b01001101010001011011010100110011 &
#825
#828
#830
b10101010101011110111000000001001 #
b00001010101010111100110101011000 $
b10110101010110110011110101100001 &
#835
#838
#840
b01111101011001010110111011110101 #
b10010111111010101010100101001101 $
b00010101010100000001100001000010 &
#845
#848
#850
b01100001111101000000110010101000 #
b10011110110110000111111100011111 $
b00000000110011001000101111000111 &
#855
#858
#860
b10100111011101110110100010101110 #
b10100000110000110010001010100100 $
b01001000001110101000101101010010 &
#865
#868
#870
b01000100001010110000110100100111 #
b11111000010010010100010011000010 $
b00111100011101000101000111101001 &
#875
#878
#880
b01111110111111001101011000010101 #
b01010111010100011111001000001111 $
b11010110010011101100100000100100 &
#885
#888
#890
b11101000001101100110111110011111 #
b10101001101101100011000010100011 $
b10010001111011001010000001000010 &
#895
#898
#900
b00011110111110011101100100101010 #
b10111101011001101010111001100111 $
b11011100011000001000011110010001 &
#905
#908
#910
b11010110010111110111100111100111 #
b10001010010100001100100000110101 $
b01100000101100000100001000011100 &
#915
#918
#920
b01011001111000100001000010011110 #
b10101111010100010110010111110100 $
b00001001001100110111011010010010 &
#925
#928
#930
b01101000000010001101101100011010 #
b00101100001111110010110111101111 $
b10010100010010000000100100001001 &
#935
#938
#940
b11100111111110100110100000011100 #
b00111101101001010010110101100100 $
b00100101100111111001010110000000 &
#945
#948
#950
b11010110011100101110010011010011 #
b11011000100001110100000000011011 $
b10101110111110100010010011101110 &
#955
#958
#960
b11110001100110011110000001101011 #
b00011010100011010010000101110101 $
b00001100001001110000000111100000 &
#965
#968
#970
b10000110100111010010001010110011 #
b10010001010110100100100010000011 $
b00010111111101110110101100110110 &
#975
#978
#980
b00101000100000001010000111111111 #
b00111110001100000011101101101011 $
b01100110101100001101110101101010 &
#985
#988
#990
b01010101010010101110111110111100 #
b10101101011010100111000100110101 $
b00000010101101010110000011110001 &
#995
#998
#1000
b11000111010011110100010010001010 #
b10100011100100110010011001100100 $
b01101010111000100110101011101110 &
#1005
#1008
#1010
b01011001100011001000110011010111 #
b10110110101010110111000010010010 $
b00010000001101111111110101101001 &
#1015
#1018
#1020
b10100100111010110110011010110111 #
b01111111110100111000011010101001 $
b00100100101111101110110101100000 &
#1025
#1028
#1030
b00100001101100010111010101100101 #
b00101111011100111100111000111011 $
b01010001001001010100001110100000 &
#1035
#1038
#1040
b11011000001010101001011111101101 #
b11100101101001100011010111101100 $
b10111101110100001100110111011001 &
#1045
#1048
#1050
b10000011001110110101001011100000 #
b10011011101100110100110010111011 $
b00011110111011101001111110011011 &
#1055
#1058
#1060
b01000101110110101110011001111111 #
b10010011110110110100101110101010 $
b11011001101101100011001000101001 &
#1065
#1068
#1070
b11110000111111000001110101111100 #
b11011111000010100010110100111111 $
b11010000000001100100101010111011 &
#1075
#1078
#1080
b00110010101011100010010010100010 #
b10011111111011010111000000100100 $
b11010010100110111001010011000110 &
#1085
#1088
#1090
b01100000001100100011010100011000 #
b00011011100100010101101101110010 $
b01111011110000111001000010001010 &
#1095
#1098
#1100
b01100001000111001010010110010101 #
b10101001010001111011000100011100 $
b00001010011001000101011010110001 &
#1105
#1108
#1110
b11110110011100100111000110111100 #
b00111011010101101010000101001010 $
b00110001110010010001001100000110 &
#1115
#1118
#1120
b10111111101111101110111001101111 #
b10100101010011010011001001011000 $
b01100101000011000010000011000111 &
#1125
#1128
#1130
b11010011000111101101011010100110 #
b00001000001010011010110010011100 $
b11011011010010001000001101000010 &
#1135
#1138
#1140
b01000100110011110111001110010011 #
b01010111000001111010000111000111 $
b10011011110101110001010101011010 &
#1145
#1148
#1150
b01111010010011000100111111101110 #
b00110111001010010111111001001011 $
b10110001011101011100111000111001 &
#1155
#1158
#1160
b11010110101110000000110010111011 #
b01111100100101110110100010010110 $
b01010011010011110111010101010001 &
#1165
#1168
#1170
b10011011110100101110011001011001 #
b00101110111100011000110101010110 $
b11001010110001000111001110101111 &
#1175
#1178
#1180
b11100111111010011000100011110101 #
b00011110110110110011111011011110 $
b00000110110001001100011111010011 &
#1185
#1188
#1190
b11100001101110111000111100001010 #
b01010111011100100011011000000011 $
b00111001001011011100010100001101 &
#1195
#1198
#1200
b00000101001010100110110011111100 #
b11111000010000000010011111111011 $
b11111101011010101001010011110111 &
#1205
#1208
#1210
b10110011110111011100100111111110 #
b01111001101111101100000101111101 $
b00101101100111001000101101111011 &
#1215
#1218
#1220
b11111101010010101011010000010100 #
b11101000001010110101000001110101 $
b11100101011101100000010010001001 &
#1225
#1228
#1230
b00101001100101001001001010101111 #
b11101010000111100000010111001011 $
b00010011101100101001100001111010 &
#1235
#1238
#1240
b01111010100100011010010111000000 #
b00101101111011000111010010000010 $
b10101000011111100001101001000010 &
#1245
#1248
#1250
b00100011011111111011110011110000 #
b00001110000111101011011000110101 $
b00110001100111100111001100100101 &
#1255
#1258
#1260
b10010111011100011100111001110111 #
b11110001010101001100111000110111 $
b001 %
b10100110000111010000000001000000 &
#1265
#1268
#1270
b01111101010011110011001011110101 #
b00001101100100110101000100110000 $
b01101111101110111110000111000101 &
#1275
#1278
#1280
b01000010000000101100110000100010 #
b10111101000000011110101000101011 $
b10000101000000001110000111110111 &
#1285
#1288
#1290
b01110100101001101001100111000001 #
b11001100011010011101011010110111 $
b10101000001111001100001100001010 &
#1295
#1298
#1300
b10111000111011010010111101101111 #
b00011111101011101101010001001011 $
b10011001001111100101101100100100 &
#1305
#1308
#1310
b11111111010001010110110110110111 #
b10101110010001101001101111000000 $
b01010000111111101101000111110111 &
#1315
#1318
#1320
b11111000010111111111010011110011 #
b00011101011101010110001111111001 $
b11011010111010101001000011111010 &
#1325
#1328
#1330
b00001010111001000011101001110001 #
b00010101100000000111100001110001 $
b11110101011000111100001000000000 &
#1335
#1338
#1340
b10110011001011100101111011010100 #
b01011101011100001101100011010111 $
b01010101101111011000010111111101 &
#1345
#1348
#1350
b00110111001000011011100001010001 #
b10101011101110110111100011010100 $
b10001011011001100011111101111101 &
#1355
#1358
#1360
b01100111001111010011001001101101 #
b01111110000000101100100011110001 $
b11101001001110100110100101111100 &
#1365
#1368
#1370
b00110010110011000110110010000110 #
b10011001000000100011110010101100 $
b10011001110010100010111111011010 &
#1375
#1378
#1380
b10110001011111011011101100110111 #
b01010011010100100100000100000100 $
b01011110001010110111101000110011 &
#1385
#1388
#1390
b11001110100110000101110010111110 #
b00000111111100111000111011010001 $
b11000110101001001100110111101101 &
#1395
#1398
#1400
b10001011100001100101001011110100 #
b01110110101011100001001111001101 $
b00010100110110000011111100100111 &
#1405
#1408
#1410
b10001010101001111100011001000111 #
b10001010110100111000010101001111 $
b11111111110101000100000011111000 &
#1415
#1418
#1420
b00011010111110000100011111100011 #
b00000010111100000001111111100111 $
b00011000000010000010011111111100 &
#1425
#1428
#1430
b10101001101011100001111100100001 #
b01100111100100010001001011100001 $
b01000010000111010000110001000000 &
#1435
#1438
#1440
b10101110101010000001011010100111 #
b10111110101001010100010100001001 $
b11110000000000101101000110011110 &
#1445
#1448
#1450
b11001110001001110100000100100110 #
b10010001011110101111010010111000 $
b00111100101011000100110001101110 &
#1455
#1458
#1460
b00111100101000001110110001101110 #
b10001100001001100000001011110101 $
b10110000011110101110100101111001 &
#1465
#1468
#1470
b11010111100001101010001001001011 #
b00100010101000101111111111011000 $
b10110100111000111010001001110011 &
#1475
#1478
#1480
b11001110011011101110000000010111 #
b10101000110001001001010101101001 $
b00100101101010100100101010101110 &
#1485
#1488
#1490
b01100011101001010100001101011110 #
b00100001100100100001011011101000 $
b01000010000100110010110001110110 &
#1495
#1498
#1500
b11111111001001010101001101100011 #
b11000101011100010010110001001000 $
b00111001101101000010011100011011 &
#1505
#1508
#1510
b00111110111011101011110100100100 #
b01111111010110101010110111010010 $
b10111111100101000000111101010010 &
#1515
#1518
#1520
b11011010101100000111001011110101 #
b01110101001001111110001000011100 $
b01100101100010001001000011011001 &
#1525
#1528
#1530
b11000111011011011110010000110101 #
b00111110001111000101100000101010 $
b10001001001100011000110000001011 &
#1535
#1538
#1540
b10001000100011101111100001101111 #
b00001001010101111111010011010011 $
b01111111001101110000001110011100 &
#1545
#1548
#1550
b00010010101000100101101111110100 #
b11101111101011100101011110100111 $
b00100010111101000000010001001101 &
#1555
#1558
#1560
b01110100111001110001010011101100 #
b00011111111000001010100010100011 $
b01010101000001100110110001001001 &
#1565
#1568
#1570
b10011110001111010011010010001000 #
b00010101110010010010111000100001 $
b10001000011101000000011001100111 &
#1575
#1578
#1580
b11111100011000111010001001110001 #
b01111000100101101111010101100000 $
b10000011110011001010110100010001 &
#1585
#1588
#1590
b11110010010111100000001111100111 #
b00110100101001101100100100110101 $
b10111101101101110011101010110010 &
#1595
#1598
#1600
b10101100010011100101010000100101 #
b11111110010111011011100010000001 $
b10101101111100001001101110100100 &
#1605
#1608
#1610
b00100111000101100000000111101000 #
b11001001100010001111011011101110 $
b01011101100011010000101011111010 &
#1615
#1618
#1620
b00110101111110011011010001010001 #
b00110000011100000101101010011001 $
b00000101100010010101100110111000 &
#1625
#1628
#1630
b10000001011100110011000111101000 #
b10100001011100100101100001001101 $
b11100000000000001101100110011011 &
#1635
#1638
#1640
b01010000100010010111111010110111 #
b11111000100101010010100011110111 $
b01010111111101000101010111000000 &
#1645
#1648
#1650
b10000110000110001010101010010110 #
b01000000000100101001011101010110 $
b01000110000001100001001101000000 &
#1655
#1658
#1660
b00000110111011110001110100101101 #
b00100111000011100100001110001000 $
b11011111111000001101100110100101 &
#1665
#1668
#1670
b11110100000101111011000010001101 #
b00011110000100011111000111000010 $
b11010110000001011011111011001011 &
#1675
#1678
#1680
b01011010110100111000000101001001 #
b00000110000011110000111001000010 $
b01010100110001000111001100000111 &
#1685
#1688
#1690
b00001111010001110100111011000011 #
b01011110000000101101001101000111 $
b10110001010001000111101101111100 &
#1695
#1698
#1700
b10110101010000010011101101111100 #
b10010011000101011110111100100000 $
b00100010001010110100110001011100 &
#1705
#1708
#1710
b00111010001011010110110000000101 #
b11101101101110000010100100000011 $
b01001100011101010100001100000010 &
#1715
#1718
#1720
b11111110000010010111011010011000 #
b00010011110100101111100110000011 $
b11101010001101100111110100010101 &
#1725
#1728
#1730
b01110101011001101111001001110010 #
b00110011000000100000110001011101 $
b01000010011001001110011000010101 &
#1735
#1738
#1740
b01110110000100000101100100011110 #
b00101100111111110100000000100110 $
b01001001000100010001100011111000 &
#1745
#1748
#1750
b11111100001111111001001111110000 #
b10000100101000010000101111001011 $
b01110111100111101000100000100101 &
#1755
#1758
#1760
b01000001100000100001011000110100 #
b01111000001111101101111001001001 $
b11001001010000110011011111101011 &
#1765
#1768
#1770
b11001001111110101110110011111111 #
b01011011111110100110101010010010 $
b01101110000000001000001001101101 &
#1775
#1778
#1780
b01101011011110100101111101101100 #
b00000010111100110000010111111111 $
b01101000100001110101100101101101 &
#1785
#1788
#1790
b11101010111010111001100000000001 #
b01100000111000100101011010101001 $
b10001010000010010100000101011000 &
#1795
#1798
#1800
b11010000011101100110011111111010 #
b11001110010101110101011100010011 $
b00000010000111110001000011100111 &
#1805
#1808
#1810
b10101100111111010001110111001111 #
b01011011001001101111111000111011 $
b01010001110101100001111110010100 &
#1815
#1818
#1820
b10010000101011010110010000001110 #
b01100101110010101101100011011111 $
b00101010111000101000101100101111 &
#1825
#1828
#1830
b00001000010101011000011011100000 #
b01000000110111110100101110100010 $
b11000111011101100011101100111110 &
#1835
#1838
#1840
b11111110101010101101101101011010 #
b00101101000000100111111011000000 $
b11010001101010000101110010011010 &
#1845
#1848
#1850
b01001000100100100000001000111010 #
b00011011010001000001010111100010 $
b00101101010011011110110001011000 &
#1855
#1858
#1860
b01010001100111111101100011000010 #
b10000001010001011100111100000000 $
b11010000010110100000100111000010 &
#1865
#1868
#1870
b01101111000010110000010010011011 #
b10111011000010001100100000011010 $
b10110100000000100011110010000001 &
#1875
#1878
#1880
b00011111001001010110100101100010 #
b11111001000111101100011000110001 $
b00100110000001101010001100110001 &
#1885
#1888
#1890
b10010011000001010001011000010011 #
b01001110111110000000111100110010 $
b01000100000011010000011011100001 &
#1895
#1898
#1900
b10000110100110000110100101011000 #
b01101001011000000111000000100010 $
b00011101001101111111100100110110 &
#1905
#1908
#1910
b01010111000110001011111001011110 #
b11110001010110000010101011100111 $
b01100101110000001001001101110111 &
#1915
#1918
#1920
b10100100111000010101010001100110 #
b11011001111100011100000110011101 $
b11001010111011111001001011001001 &
#1925
#1928
#1930
b01111110011101100000011101010110 #
b01001010111011011101011011001011 $
b00110011100010000011000010001011 &
#1935
#1938
#1940
b00010011010000100010111100111001 #
b01010001000000101010000101100001 $
b11000010001111111000110111011000 &
#1945
#1948
#1950
b00111111001001101110111000111011 #
b01100010001110110100100101010110 $
b11011100111010111010010011100101 &
#1955
#1958
#1960
b10101101010000111010110001111001 #
b01110111010111110001010011000111 $
b00110101111001001001011110110010 &
#1965
#1968
#1970
b00111001011011000000010111000010 #
b00001111010110000000000110101001 $
b00101010000101000000010000011001 &
#1975
#1978
#1980
b01011100101000001101110010001110 #
b10010001011011110111000110110101 $
b11001011001100010110101011011001 &
#1985
#1988
#1990
b00110101011110111011001100111101 #
b10110010101111001100000100001111 $
b10000010101111101111001000101110 &
#1995
#1998
#2000
b11100000010000001111110111000100 #
b00000100100101011111011100100011 $
b11011011101010110000011010100001 &
#2005
#2008
#2010
b00010101010011001100000000011001 #
b11011000101110110110101000010001 $
b00111100100100010101011000001000 &
#2015
#2018
#2020
b10110100000010011010010101001111 #
b00100101101001100010110000100010 $
b10001110011000110111100100101101 &
#2025
#2028
#2030
b10111011000010011110101011001000 #
b10001000011000110001001111000001 $
b00110010101001101101011100000111 &
#2035
#2038
#2040
b11011001111100110100110100010010 #
b00110011111011000111010101011010 $
b10100110000001101101011110111000 &
#2045
#2048
#2050
b11001100000000110111000101100000 #
b10000000110110111111011010100011 $
b01001011001001110111101010111101 &
#2055
#2058
#2060
b01000111000100001001101111010000 #
b10011110100000001000100010000101 $
b10101000100100000001001101001011 &
#2065
#2068
#2070
b11010001000001010001100111000110 #
b01101011110001101100000110010111 $
b01100101001111100101100000101111 &
#2075
#2078
#2080
b00111011110110101110111011101000 #
b00101000000010010001000001111011 $
b00010011110100011101111001101101 &
#2085
#2088
#2090
b01111110100010011011100001010000 #
b11111010100011110011110000100100 $
b10000011111110100111110000101100 &
#2095
#2098
#2100
b01001100011001100011111001110011 #
b11111101100100101010011010101111 $
b01001110110100111001011111000100 &
#2105
#2108
#2110
b01110101010001000111111101111001 #
b10100001010010111000001011100010 $
b11010011111110001111110010010111 &
#2115
#2118
#2120
b10000011101111101001001000101010 #
b10111001010010101110011001110000 $
b11001010011100111010101110111010 &
#2125
#2128
#2130
b11111111110110101011011111001010 #
b10111001011010101101100101111010 $
b01000110011011111101111001010000 &
#2135
#2138
#2140
b11100000010000011100001001001100 #
b10000111110100111010100111111000 $
b01011000011011100001100001010100 &
#2145
#2148
#2150
b00000000110101010110001100110111 #
b10101000110011101111100011111100 $
b01011000000001100110101000111011 &
#2155
#2158
#2160
b10101010100010001110111010110010 #
b10010100110011110101000101011010 $
b00010101101110011001110101011000 &
#2165
#2168
#2170
b11001101011011110111111100110101 #
b00100101001111000000111010110101 $
b10101000001100110111000010000000 &
#2175
#2178
#2180
b11000101001100010000000111101110 #
b00100000011100101010011010000111 $
b10100100101111100101101101100111 &
#2185
#2188
#2190
b01000110111111001001101111011000 #
b11011001101011111101111111000111 $
b01101101010011001011110000010001 &
#2195
#2198
#2200
b11101011110110001101101001000101 #
b01000010011011111100110101001010 $
b10101001011010010000110011111011 &
#2205
#2208
#2210
b10010001110100010011101010111110 #
b11001001111010001011110100001001 $
b11000111111010000111110110110101 &
#2215
#2218
#2220
b11001100011000111001001110100010 #
b01011010110001110111000110001001 $
b01110001100111000010001000011001 &
#2225
#2228
#2230
b11011111010100101010111111001011 #
b01001101111001010010011111010100 $
b10010001011011011000011111110111 &
#2235
#2238
#2240
b10011100100111101001110110001011 #
b01010111100011010111011100101101 $
b01000101000100010010011001011110 &
#2245
#2248
#2250
b00101101111011011011010010100110 #
b10110011011100100101000101101000 $
b01111010011110110110001100111110 &
#2255
#2258
#2260
b01000011100001100101000010111100 #
b00110101111011000011111111001011 $
b00001101100110100001000011110001 &
#2265
#2268
#2270
b00100010101000000101000111110001 #
b01111011111110000110111000010011 $
b10100110101001111110001111011110 &
#2275
#2278
#2280
b01101100100111011011000100110001 #
b00100100100001100010010110001000 $
b01001000000101111000101110101001 &
#2285
#2288
#2290
b00110001111101101111101010011100 #
b01101011011000101001001100011000 $
b11000110100101000110011110000100 &
#2295
#2298
#2300
b11100110111010000011000011101101 #
b00110100001100111111110011101111 $
b10110010101101000011001111111110 &
#2305
#2308
#2310
b01010000110100011101001010001010 #
b10000101101100011001001110100101 $
b11001011001000000011111011100101 &
#2315
#2318
#2320
b01110000101010100010000111101100 #
b10010000111010101110011100011100 $
b11011111101111110011101011010000 &
#2325
#2328
#2330
b01010011001110100101000111110011 #
b11110100100001000110001100011010 $
b01011110101101011110111011011001 &
#2335
#2338
#2340
b01000110001010000011011101101000 #
b00010101100010111111011110011000 $
b00110000100111000011111111010000 &
#2345
#2348
#2350
b10100010110001100011011011010000 #
b00000011111110111110011101001111 $
b10011110110010100100111110000001 &
#2355
#2358
#2360
b11000111001011110100110010110010 #
b01110101001000000101001011100100 $
b01010010000011101111100111001110 &
#2365
#2368
#2370
b11110000111110010000001000001001 #
b10100011000111110101100011110011 $
b01001101110110011010100100010110 &
#2375
#2378
#2380
b11001001101001000011110011001101 #
b10111101010010000000000110101111 $
b00001100010111000011101100011110 &
#2385
#2388
#2390
b11001000110001110100000110111110 #
b00100110101011001011100001110110 $
b10100010000110101000100101001000 &
#2395
#2398
#2400
b10111100100100011101111100100110 #
b00100111100101100011111001100000 $
b10010100111110111010000011000110 &
#2405
#2408
#2410
b11001100100110100101001010011001 #
b10010111010101000110111000110010 $
b00110101010001011110010001100111 &
#2415
#2418
#2420
b00110001000010011111110000001011 #
b00001100011011110101000100100110 $
b00100100100110101010101011100101 &
#2425
#2428
#2430
b11000100110100110010010110000010 #
b10100110110001001101000101011010 $
b00011110000011100101010000101000 &
#2435
#2438
#2440
b00110101110110100100000111111000 #
b11111001100010000001010001111111 $
b00111100010100100010110101111001 &
#2445
#2448
#2450
b10111010110100010111001110000101 #
b01010101000110111101110111010101 $
b01100101101101011001010110110000 &
#2455
#2458
#2460
b11001001011101000010010011010010 #
b10000000101011011101010011101001 $
b01001000110001100100111111101001 &
#2465
#2468
#2470
b10011111111100010011001110011111 #
b10101110100111100001000001000101 $
b11110001010100110010001101011010 &
#2475
#2478
#2480
b10010001110111010110110111011001 #
b00110010100111100110010100101000 $
b01011111001111110000100010110001 &
#2485
#2488
#2490
b11011111010000010101011110001101 #
b00100010100110000010111010101111 $
b10111100101010010010100011011110 &
#2495
#2498
#2500
b01100100101111111110111111100010 #
b00000000111111000111111010101101 $
b01100011110000110111000100110101 &
#2505
#2508
#2510
b11111000100001100111100100101010 #
b00000000000000000000000000010100 $
b010 %
b10010010101000000000000000000000 &
#2515
#2518
#2520
b01100100101011001100011101101101 #
b00000000000000000000000000000110 $
b00101011001100011101101101000000 &
#2525
#2528
#2530
b01001011101100100110101011010110 #
b00000000000000000000000000011101 $
b11000000000000000000000000000000 &
#2535
#2538
#2540
b01001101001111011101101010000100 #
b00000000000000000000000000010010 $
b01101010000100000000000000000000 &
#2545
#2548
#2550
b01101110010001000000010000011100 #
b00000000000000000000000000011111 $
b00000000000000000000000000000000 &
#2555
#2558
#2560
b11100101100110110100111100001010 #
b00000000000000000000000000000111 $
b11001101101001111000010100000000 &
#2565
#2568
#2570
b10110111010110100100100100111000 #
b00000000000000000000000000011000 $
b00111000000000000000000000000000 &
#2575
#2578
#2580
b01010111100000010101000010000100 #
b00000000000000000000000000010111 $
b01000010000000000000000000000000 &
#2585
#2588
#2590
b01000101001001001101000100001001 #
b00000000000000000000000000001010 $
b10010011010001000010010000000000 &
#2595
#2598
